MANIFEST.in
README.txt
setup.py
c2/__init__.py
c2.patch.atrefs.egg-info/PKG-INFO
c2.patch.atrefs.egg-info/SOURCES.txt
c2.patch.atrefs.egg-info/dependency_links.txt
c2.patch.atrefs.egg-info/entry_points.txt
c2.patch.atrefs.egg-info/namespace_packages.txt
c2.patch.atrefs.egg-info/not-zip-safe
c2.patch.atrefs.egg-info/requires.txt
c2.patch.atrefs.egg-info/top_level.txt
c2/patch/__init__.py
c2/patch/atrefs/__init__.py
c2/patch/atrefs/configure.zcml
c2/patch/atrefs/methods.py
c2/patch/atrefs/tests.py
c2/patch/atrefs/version.txt
docs/HISTORY.txt
docs/INSTALL.txt
docs/LICENSE.GPL
docs/LICENSE.txt