Metadata-Version: 1.0
Name: c2.patch.atrefs
Version: 1.0a1
Summary: This patch is checking permissions and checking effectiveDate for ATReference
Home-page: http://www.cmscom.jp
Author: Manabu TERADA
Author-email: terada@cmscom.jp
License: GPL
Keywords: plone archetypes reference patch
Platform: UNKNOWN
Classifier: Framework :: Plone
Classifier: Programming Language :: Python
